{
  "_instructions": "Fill in every field below. Delete this _instructions line before running. Then run: python3 mws_audit_fill.py this_file.json",
  "CLIENT_NAME": "Bettcher Manufacturing",
  "CLIENT_WEBSITE": "bettcherllc.com",
  "INDUSTRY": "Metal Stamping",
  "LOCATION": "Mission, TX",
  "MONTH_YEAR": "March 2026",
  "CURRENT_YEAR": "2026",
  "FOUNDED_YEAR": "1894",
  "EMPLOYEES": "200+",
  "REVENUE_ESTIMATE": "$10M\u2013$30M",
  "MARKET_NAME": "Metal Stamping & Fabrication",
  "CERTIFICATIONS": "ISO 9001",
  "KEY_CLIENTS": "Trane, Emerson, Nidec, Bendix, Vertiv",
  "INDUSTRIES_SERVED": "HVAC, Refrigeration, Commercial Trucking, Appliances",
  "CMS_PLATFORM": "WordPress",
  "LAST_SITE_UPDATE": "2016",
  "ANALYTICS_STATUS": "None detected",
  "CDN": "None",
  "COMPETITORS": "Monterrey Fab, Texas Metal Works, RGV Steel Fab",
  "CONTACT_NAME": "",
  "CONTACT_EMAIL": "sales@bettcherllc.com",
  "PHONE": "",
  "RATE_TIER": "Standard",
  "AVATAR": "Procurement Manager or Plant Engineer at a mid-size manufacturer in South Texas seeking a reliable stamping partner",
  "SCORE_OVERALL": "4.2/10",
  "SCORE_DESIGN_UX": "3.5/10",
  "SCORE_ONPAGE_SEO": "4.0/10",
  "SCORE_TECHNICAL_SEO": "5.0/10",
  "SCORE_CONTENT": "3.0/10",
  "SCORE_CONVERSION": "2.5/10",
  "SCORE_TRUST": "4.5/10",
  "SCORE_DIGITAL": "3.0/10",
  "TOP_BLIND_SPOT_1": "130 years of expertise buried in a 2016 website no buyer can find",
  "TOP_BLIND_SPOT_2": "No quote request flow \u2014 buyers have no way to initiate contact online",
  "TOP_BLIND_SPOT_3": "ISO certification hidden at bottom \u2014 key credential invisible to buyers doing due diligence",
  "PITCH_ANGLE": "130 years of manufacturing excellence \u2014 the website is from 2016",
  "STRATEGIC_FINDING": "Bettcher has the client roster and certifications of a $50M operation. The website presents like a startup.",
  "DREAM_OUTCOME_1": "Inbound quote requests from qualified manufacturers \u2014 no cold calling required",
  "DREAM_OUTCOME_2": "ISO and client credentials visible to every buyer on first visit",
  "DREAM_OUTCOME_3": "Google presence that captures searches for metal stamping in South Texas",
  "DREAM_OUTCOME_4": "A site that closes deals while the shop floor runs",
  "OFFER_NAME": "The 90-Day Revenue Engine System for Texas Manufacturers",
  "GUARANTEE_LAYER_1": "30-day satisfaction guarantee \u2014 any page redesigned free if not satisfied",
  "GUARANTEE_LAYER_2": "1 qualified inbound lead within 90 days of launch or we keep working free",
  "MARKET_GLOBAL_SIZE": "$15B+",
  "MARKET_REGION_SIZE": "$2.1B",
  "MARKET_CAGR": "4.8%",
  "MARKET_SEGMENT": "Automotive & HVAC",
  "MARKET_YEAR_START": "2026",
  "MARKET_YEAR_END": "2031",
  "Competitor 1": "Monterrey Fab",
  "Competitor 2": "Texas Metal Works",
  "Competitor 3": "RGV Steel Fabrication",
  "Description of their digital strengths": "Competitor sites show full capabilities, certifications front and center, and online quote forms",
  "Fix #2": "Add ISO 9001 certification badge to homepage hero section",
  "Fix #3": "Build a dedicated certifications page with downloadable quality documents",
  "Fix #4": "Add a 'Request a Quote' CTA button to every page",
  "Service 1": "Metal Stamping & Fabrication",
  "Service 2": "Assembly & Sub-Assembly",
  "Service 3": "CNC Machining & Tooling",
  "X,000\u2013Y,000": "$4,500\u2013$22,500",
  "Buyer description": "Procurement Manager or Plant Engineer at $5M\u2013$50M manufacturer in Texas",
  "Problem description": "Cannot find a reliable local stamping partner with proven OEM client history",
  "Outcome": "First Inbound Customer",
  "Primary Deliverable": "Revenue Engine Website Build \u2014 custom, mobile-ready, Cloudflare-powered",
  "Bonus Name": "Texas Manufacturer Visibility Blueprint",
  "Source 1 (Month Year)": "IBISWorld Metal Stamping Report (Jan 2026)",
  "Source 2 (Month Year)": "Grand View Research Manufacturing Outlook (Feb 2026)",
  "Source 3": "Texas Manufacturing Association Annual Report 2025",
  "Driver 1": "Nearshoring & Border Corridor Manufacturing Expansion",
  "Driver 2": "HVAC & Refrigeration Industry Growth",
  "Driver 3": "Automotive Supply Chain Reshoring",
  "Driver 4": "Industrial Equipment Demand"
}